setup.cfg
setup.py
PartsDB.egg-info/PKG-INFO
PartsDB.egg-info/SOURCES.txt
PartsDB.egg-info/dependency_links.txt
PartsDB.egg-info/requires.txt
PartsDB.egg-info/top_level.txt
partsdb/__init__.py
partsdb/partsdb.py
partsdb/system/IDGenerator.py
partsdb/system/Tables.py
partsdb/system/__init__.py
partsdb/tools/__init__.py
partsdb/tools/annotateBlastp.py
partsdb/tools/compRev.py
partsdb/tools/cutGenes.py
partsdb/tools/cutGenesBio.py
partsdb/tools/getUtrCoordinates.py
partsdb/tools/saveSeqs.py
partsdb/tools/Annotators/Annotator.py
partsdb/tools/Annotators/BlastAnnotator.py
partsdb/tools/Annotators/PfamAnnotator.py
partsdb/tools/Annotators/TableAnnotator.py
partsdb/tools/Annotators/__init__.py
partsdb/tools/CoordinateMapper/CoordinateMapper.py
partsdb/tools/CoordinateMapper/MapPositions.py
partsdb/tools/CoordinateMapper/RangeCoordinateMapper.py
partsdb/tools/CoordinateMapper/__init__.py
partsdb/tools/CoordinateMapper/testCoordinateMapper.py
partsdb/tools/Exporters/Exporter.py
partsdb/tools/Exporters/GenBankExporter.py
partsdb/tools/Exporters/__init__.py
partsdb/tools/Populators/PlantPopulator.py
partsdb/tools/Populators/Populator.py
partsdb/tools/Populators/__init__.py