Metadata-Version: 1.1
Name: PartsDB
Version: 0.2.0
Summary: Database of genetic parts
Home-page: https://github.com/HaseloffLab/MarpoDB
Author: Mihails Delmans
Author-email: md656@cam.ac.uk
License: GPL
Keywords: bioinfomratics parts synthetic biology
Platform: UNKNOWN
Classifier: Development Status :: 3 - Alpha
Classifier: Intended Audience :: Developers
Classifier: Intended Audience :: Science/Research
Classifier: Topic :: Scientific/Engineering :: Bio-Informatics
Classifier: License :: OSI Approved :: GNU General Public License (GPL)
Classifier: Programming Language :: Python :: 2.7
